{"total_count":5,"workflow_runs":[{"id":27486402044,"name":"Build Android APK","node_id":"WFR_kwLOS6Eoc88AAAAGZlE1_A","head_branch":"main","head_sha":"a5e0faed19de9030911e821c8226f2f7f57bfb26","path":".github/workflows/build_apk.yml","display_title":"fix build to apk","run_number":5,"event":"push","status":"completed","conclusion":"failure","workflow_id":295580016,"check_suite_id":73958157846,"check_suite_node_id":"CS_kwDOS6Eoc88AAAAROD_uFg","url":"https://api.github.com/repos/puyvongheng/apk_youtube_download/actions/runs/27486402044","html_url":"https://github.com/puyvongheng/apk_youtube_download/actions/runs/27486402044","pull_requests":[],"created_at":"2026-06-14T02:52:04Z","updated_at":"2026-06-14T03:01:34Z","actor":{"login":"puyvongheng","id":160134498,"node_id":"U_kgDOCYt1Yg","avatar_url":"https://avatars.githubusercontent.com/u/160134498?v=4","gravatar_id":"","url":"https://api.github.com/users/puyvongheng","html_url":"https://github.com/puyvongheng","followers_url":"https://api.github.com/users/puyvongheng/followers","following_url":"https://api.github.com/users/puyvongheng/following{/other_user}","gists_url":"https://api.github.com/users/puyvongheng/gists{/gist_id}","starred_url":"https://api.github.com/users/puyvongheng/starred{/owner}{/repo}","subscriptions_url":"https://api.github.com/users/puyvongheng/subscriptions","organizations_url":"https://api.github.com/users/puyvongheng/orgs","repos_url":"https://api.github.com/users/puyvongheng/repos","events_url":"https://api.github.com/users/puyvongheng/events{/privacy}","received_events_url":"https://api.github.com/users/puyvongheng/received_events","type":"User","user_view_type":"public","site_admin":false},"run_attempt":1,"referenced_workflows":[],"run_started_at":"2026-06-14T02:52:04Z","triggering_actor":{"login":"puyvongheng","id":160134498,"node_id":"U_kgDOCYt1Yg","avatar_url":"https://avatars.githubusercontent.com/u/160134498?v=4","gravatar_id":"","url":"https://api.github.com/users/puyvongheng","html_url":"https://github.com/puyvongheng","followers_url":"https://api.github.com/users/puyvongheng/followers","following_url":"https://api.github.com/users/puyvongheng/following{/other_user}","gists_url":"https://api.github.com/users/puyvongheng/gists{/gist_id}","starred_url":"https://api.github.com/users/puyvongheng/starred{/owner}{/repo}","subscriptions_url":"https://api.github.com/users/puyvongheng/subscriptions","organizations_url":"https://api.github.com/users/puyvongheng/orgs","repos_url":"https://api.github.com/users/puyvongheng/repos","events_url":"https://api.github.com/users/puyvongheng/events{/privacy}","received_events_url":"https://api.github.com/users/puyvongheng/received_events","type":"User","user_view_type":"public","site_admin":false},"jobs_url":"https://api.github.com/repos/puyvongheng/apk_youtube_download/actions/runs/27486402044/jobs","logs_url":"https://api.github.com/repos/puyvongheng/apk_youtube_download/actions/runs/27486402044/logs","check_suite_url":"https://api.github.com/repos/puyvongheng/apk_youtube_download/check-suites/73958157846","artifacts_url":"https://api.github.com/repos/puyvongheng/apk_youtube_download/actions/runs/27486402044/artifacts","cancel_url":"https://api.github.com/repos/puyvongheng/apk_youtube_download/actions/runs/27486402044/cancel","rerun_url":"https://api.github.com/repos/puyvongheng/apk_youtube_download/actions/runs/27486402044/rerun","previous_attempt_url":null,"workflow_url":"https://api.github.com/repos/puyvongheng/apk_youtube_download/actions/workflows/295580016","head_commit":{"id":"a5e0faed19de9030911e821c8226f2f7f57bfb26","tree_id":"fcb08cff79f70119d0e06ff169bd13a5436de7bf","message":"fix build to apk","timestamp":"2026-06-14T02:51:39Z","author":{"name":"Puyvong Heng","email":"vongheng2019@example.com"},"committer":{"name":"Puyvong Heng","email":"vongheng2019@example.com"}},"repository":{"id":1268852851,"node_id":"R_kgDOS6Eocw","name":"apk_youtube_download","full_name":"puyvongheng/apk_youtube_download","private":false,"owner":{"login":"puyvongheng","id":160134498,"node_id":"U_kgDOCYt1Yg","avatar_url":"https://avatars.githubusercontent.com/u/160134498?v=4","gravatar_id":"","url":"https://api.github.com/users/puyvongheng","html_url":"https://github.com/puyvongheng","followers_url":"https://api.github.com/users/puyvongheng/followers","following_url":"https://api.github.com/users/puyvongheng/following{/other_user}","gists_url":"https://api.github.com/users/puyvongheng/gists{/gist_id}","starred_url":"https://api.github.com/users/puyvongheng/starred{/owner}{/repo}","subscriptions_url":"https://api.github.com/users/puyvongheng/subscriptions","organizations_url":"https://api.github.com/users/puyvongheng/orgs","repos_url":"https://api.github.com/users/puyvongheng/repos","events_url":"https://api.github.com/users/puyvongheng/events{/privacy}","received_events_url":"https://api.github.com/users/puyvongheng/received_events","type":"User","user_view_type":"public","site_admin":false},"html_url":"https://github.com/puyvongheng/apk_youtube_download","description":null,"fork":false,"url":"https://api.github.com/repos/puyvongheng/apk_youtube_download","forks_url":"https://api.github.com/repos/puyvongheng/apk_youtube_download/forks","keys_url":"https://api.github.com/repos/puyvongheng/apk_youtube_download/keys{/key_id}","collaborators_url":"https://api.github.com/repos/puyvongheng/apk_youtube_download/collaborators{/collaborator}","teams_url":"https://api.github.com/repos/puyvongheng/apk_youtube_download/teams","hooks_url":"https://api.github.com/repos/puyvongheng/apk_youtube_download/hooks","issue_events_url":"https://api.github.com/repos/puyvongheng/apk_youtube_download/issues/events{/number}","events_url":"https://api.github.com/repos/puyvongheng/apk_youtube_download/events","assignees_url":"https://api.github.com/repos/puyvongheng/apk_youtube_download/assignees{/user}","branches_url":"https://api.github.com/repos/puyvongheng/apk_youtube_download/branches{/branch}","tags_url":"https://api.github.com/repos/puyvongheng/apk_youtube_download/tags","blobs_url":"https://api.github.com/repos/puyvongheng/apk_youtube_download/git/blobs{/sha}","git_tags_url":"https://api.github.com/repos/puyvongheng/apk_youtube_download/git/tags{/sha}","git_refs_url":"https://api.github.com/repos/puyvongheng/apk_youtube_download/git/refs{/sha}","trees_url":"https://api.github.com/repos/puyvongheng/apk_youtube_download/git/trees{/sha}","statuses_url":"https://api.github.com/repos/puyvongheng/apk_youtube_download/statuses/{sha}","languages_url":"https://api.github.com/repos/puyvongheng/apk_youtube_download/languages","stargazers_url":"https://api.github.com/repos/puyvongheng/apk_youtube_download/stargazers","contributors_url":"https://api.github.com/repos/puyvongheng/apk_youtube_download/contributors","subscribers_url":"https://api.github.com/repos/puyvongheng/apk_youtube_download/subscribers","subscription_url":"https://api.github.com/repos/puyvongheng/apk_youtube_download/subscription","commits_url":"https://api.github.com/repos/puyvongheng/apk_youtube_download/commits{/sha}","git_commits_url":"https://api.github.com/repos/puyvongheng/apk_youtube_download/git/commits{/sha}","comments_url":"https://api.github.com/repos/puyvongheng/apk_youtube_download/comments{/number}","issue_comment_url":"https://api.github.com/repos/puyvongheng/apk_youtube_download/issues/comments{/number}","contents_url":"https://api.github.com/repos/puyvongheng/apk_youtube_download/contents/{+path}","compare_url":"https://api.github.com/repos/puyvongheng/apk_youtube_download/compare/{base}...{head}","merges_url":"https://api.github.com/repos/puyvongheng/apk_youtube_download/merges","archive_url":"https://api.github.com/repos/puyvongheng/apk_youtube_download/{archive_format}{/ref}","downloads_url":"https://api.github.com/repos/puyvongheng/apk_youtube_download/downloads","issues_url":"https://api.github.com/repos/puyvongheng/apk_youtube_download/issues{/number}","pulls_url":"https://api.github.com/repos/puyvongheng/apk_youtube_download/pulls{/number}","milestones_url":"https://api.github.com/repos/puyvongheng/apk_youtube_download/milestones{/number}","notifications_url":"https://api.github.com/repos/puyvongheng/apk_youtube_download/notifications{?since,all,participating}","labels_url":"https://api.github.com/repos/puyvongheng/apk_youtube_download/labels{/name}","releases_url":"https://api.github.com/repos/puyvongheng/apk_youtube_download/releases{/id}","deployments_url":"https://api.github.com/repos/puyvongheng/apk_youtube_download/deployments"},"head_repository":{"id":1268852851,"node_id":"R_kgDOS6Eocw","name":"apk_youtube_download","full_name":"puyvongheng/apk_youtube_download","private":false,"owner":{"login":"puyvongheng","id":160134498,"node_id":"U_kgDOCYt1Yg","avatar_url":"https://avatars.githubusercontent.com/u/160134498?v=4","gravatar_id":"","url":"https://api.github.com/users/puyvongheng","html_url":"https://github.com/puyvongheng","followers_url":"https://api.github.com/users/puyvongheng/followers","following_url":"https://api.github.com/users/puyvongheng/following{/other_user}","gists_url":"https://api.github.com/users/puyvongheng/gists{/gist_id}","starred_url":"https://api.github.com/users/puyvongheng/starred{/owner}{/repo}","subscriptions_url":"https://api.github.com/users/puyvongheng/subscriptions","organizations_url":"https://api.github.com/users/puyvongheng/orgs","repos_url":"https://api.github.com/users/puyvongheng/repos","events_url":"https://api.github.com/users/puyvongheng/events{/privacy}","received_events_url":"https://api.github.com/users/puyvongheng/received_events","type":"User","user_view_type":"public","site_admin":false},"html_url":"https://github.com/puyvongheng/apk_youtube_download","description":null,"fork":false,"url":"https://api.github.com/repos/puyvongheng/apk_youtube_download","forks_url":"https://api.github.com/repos/puyvongheng/apk_youtube_download/forks","keys_url":"https://api.github.com/repos/puyvongheng/apk_youtube_download/keys{/key_id}","collaborators_url":"https://api.github.com/repos/puyvongheng/apk_youtube_download/collaborators{/collaborator}","teams_url":"https://api.github.com/repos/puyvongheng/apk_youtube_download/teams","hooks_url":"https://api.github.com/repos/puyvongheng/apk_youtube_download/hooks","issue_events_url":"https://api.github.com/repos/puyvongheng/apk_youtube_download/issues/events{/number}","events_url":"https://api.github.com/repos/puyvongheng/apk_youtube_download/events","assignees_url":"https://api.github.com/repos/puyvongheng/apk_youtube_download/assignees{/user}","branches_url":"https://api.github.com/repos/puyvongheng/apk_youtube_download/branches{/branch}","tags_url":"https://api.github.com/repos/puyvongheng/apk_youtube_download/tags","blobs_url":"https://api.github.com/repos/puyvongheng/apk_youtube_download/git/blobs{/sha}","git_tags_url":"https://api.github.com/repos/puyvongheng/apk_youtube_download/git/tags{/sha}","git_refs_url":"https://api.github.com/repos/puyvongheng/apk_youtube_download/git/refs{/sha}","trees_url":"https://api.github.com/repos/puyvongheng/apk_youtube_download/git/trees{/sha}","statuses_url":"https://api.github.com/repos/puyvongheng/apk_youtube_download/statuses/{sha}","languages_url":"https://api.github.com/repos/puyvongheng/apk_youtube_download/languages","stargazers_url":"https://api.github.com/repos/puyvongheng/apk_youtube_download/stargazers","contributors_url":"https://api.github.com/repos/puyvongheng/apk_youtube_download/contributors","subscribers_url":"https://api.github.com/repos/puyvongheng/apk_youtube_download/subscribers","subscription_url":"https://api.github.com/repos/puyvongheng/apk_youtube_download/subscription","commits_url":"https://api.github.com/repos/puyvongheng/apk_youtube_download/commits{/sha}","git_commits_url":"https://api.github.com/repos/puyvongheng/apk_youtube_download/git/commits{/sha}","comments_url":"https://api.github.com/repos/puyvongheng/apk_youtube_download/comments{/number}","issue_comment_url":"https://api.github.com/repos/puyvongheng/apk_youtube_download/issues/comments{/number}","contents_url":"https://api.github.com/repos/puyvongheng/apk_youtube_download/contents/{+path}","compare_url":"https://api.github.com/repos/puyvongheng/apk_youtube_download/compare/{base}...{head}","merges_url":"https://api.github.com/repos/puyvongheng/apk_youtube_download/merges","archive_url":"https://api.github.com/repos/puyvongheng/apk_youtube_download/{archive_format}{/ref}","downloads_url":"https://api.github.com/repos/puyvongheng/apk_youtube_download/downloads","issues_url":"https://api.github.com/repos/puyvongheng/apk_youtube_download/issues{/number}","pulls_url":"https://api.github.com/repos/puyvongheng/apk_youtube_download/pulls{/number}","milestones_url":"https://api.github.com/repos/puyvongheng/apk_youtube_download/milestones{/number}","notifications_url":"https://api.github.com/repos/puyvongheng/apk_youtube_download/notifications{?since,all,participating}","labels_url":"https://api.github.com/repos/puyvongheng/apk_youtube_download/labels{/name}","releases_url":"https://api.github.com/repos/puyvongheng/apk_youtube_download/releases{/id}","deployments_url":"https://api.github.com/repos/puyvongheng/apk_youtube_download/deployments"}},{"id":27486338088,"name":"Build Android APK","node_id":"WFR_kwLOS6Eoc88AAAAGZlA8KA","head_branch":"main","head_sha":"d4cb0e73159ae92c45d926c20afd484568dc174a","path":".github/workflows/build_apk.yml","display_title":"fix: pre-accept all Android SDK licenses to bypass interactive prompt…","run_number":4,"event":"push","status":"completed","conclusion":"failure","workflow_id":295580016,"check_suite_id":73957973999,"check_suite_node_id":"CS_kwDOS6Eoc88AAAAROD0f7w","url":"https://api.github.com/repos/puyvongheng/apk_youtube_download/actions/runs/27486338088","html_url":"https://github.com/puyvongheng/apk_youtube_download/actions/runs/27486338088","pull_requests":[],"created_at":"2026-06-14T02:48:42Z","updated_at":"2026-06-14T02:49:44Z","actor":{"login":"puyvongheng","id":160134498,"node_id":"U_kgDOCYt1Yg","avatar_url":"https://avatars.githubusercontent.com/u/160134498?v=4","gravatar_id":"","url":"https://api.github.com/users/puyvongheng","html_url":"https://github.com/puyvongheng","followers_url":"https://api.github.com/users/puyvongheng/followers","following_url":"https://api.github.com/users/puyvongheng/following{/other_user}","gists_url":"https://api.github.com/users/puyvongheng/gists{/gist_id}","starred_url":"https://api.github.com/users/puyvongheng/starred{/owner}{/repo}","subscriptions_url":"https://api.github.com/users/puyvongheng/subscriptions","organizations_url":"https://api.github.com/users/puyvongheng/orgs","repos_url":"https://api.github.com/users/puyvongheng/repos","events_url":"https://api.github.com/users/puyvongheng/events{/privacy}","received_events_url":"https://api.github.com/users/puyvongheng/received_events","type":"User","user_view_type":"public","site_admin":false},"run_attempt":1,"referenced_workflows":[],"run_started_at":"2026-06-14T02:48:42Z","triggering_actor":{"login":"puyvongheng","id":160134498,"node_id":"U_kgDOCYt1Yg","avatar_url":"https://avatars.githubusercontent.com/u/160134498?v=4","gravatar_id":"","url":"https://api.github.com/users/puyvongheng","html_url":"https://github.com/puyvongheng","followers_url":"https://api.github.com/users/puyvongheng/followers","following_url":"https://api.github.com/users/puyvongheng/following{/other_user}","gists_url":"https://api.github.com/users/puyvongheng/gists{/gist_id}","starred_url":"https://api.github.com/users/puyvongheng/starred{/owner}{/repo}","subscriptions_url":"https://api.github.com/users/puyvongheng/subscriptions","organizations_url":"https://api.github.com/users/puyvongheng/orgs","repos_url":"https://api.github.com/users/puyvongheng/repos","events_url":"https://api.github.com/users/puyvongheng/events{/privacy}","received_events_url":"https://api.github.com/users/puyvongheng/received_events","type":"User","user_view_type":"public","site_admin":false},"jobs_url":"https://api.github.com/repos/puyvongheng/apk_youtube_download/actions/runs/27486338088/jobs","logs_url":"https://api.github.com/repos/puyvongheng/apk_youtube_download/actions/runs/27486338088/logs","check_suite_url":"https://api.github.com/repos/puyvongheng/apk_youtube_download/check-suites/73957973999","artifacts_url":"https://api.github.com/repos/puyvongheng/apk_youtube_download/actions/runs/27486338088/artifacts","cancel_url":"https://api.github.com/repos/puyvongheng/apk_youtube_download/actions/runs/27486338088/cancel","rerun_url":"https://api.github.com/repos/puyvongheng/apk_youtube_download/actions/runs/27486338088/rerun","previous_attempt_url":null,"workflow_url":"https://api.github.com/repos/puyvongheng/apk_youtube_download/actions/workflows/295580016","head_commit":{"id":"d4cb0e73159ae92c45d926c20afd484568dc174a","tree_id":"2ee118282800f20654c786440dfc8c4c41269c87","message":"fix: pre-accept all Android SDK licenses to bypass interactive prompt in CI","timestamp":"2026-06-14T02:48:26Z","author":{"name":"Puyvong Heng","email":"vongheng2019@example.com"},"committer":{"name":"Puyvong Heng","email":"vongheng2019@example.com"}},"repository":{"id":1268852851,"node_id":"R_kgDOS6Eocw","name":"apk_youtube_download","full_name":"puyvongheng/apk_youtube_download","private":false,"owner":{"login":"puyvongheng","id":160134498,"node_id":"U_kgDOCYt1Yg","avatar_url":"https://avatars.githubusercontent.com/u/160134498?v=4","gravatar_id":"","url":"https://api.github.com/users/puyvongheng","html_url":"https://github.com/puyvongheng","followers_url":"https://api.github.com/users/puyvongheng/followers","following_url":"https://api.github.com/users/puyvongheng/following{/other_user}","gists_url":"https://api.github.com/users/puyvongheng/gists{/gist_id}","starred_url":"https://api.github.com/users/puyvongheng/starred{/owner}{/repo}","subscriptions_url":"https://api.github.com/users/puyvongheng/subscriptions","organizations_url":"https://api.github.com/users/puyvongheng/orgs","repos_url":"https://api.github.com/users/puyvongheng/repos","events_url":"https://api.github.com/users/puyvongheng/events{/privacy}","received_events_url":"https://api.github.com/users/puyvongheng/received_events","type":"User","user_view_type":"public","site_admin":false},"html_url":"https://github.com/puyvongheng/apk_youtube_download","description":null,"fork":false,"url":"https://api.github.com/repos/puyvongheng/apk_youtube_download","forks_url":"https://api.github.com/repos/puyvongheng/apk_youtube_download/forks","keys_url":"https://api.github.com/repos/puyvongheng/apk_youtube_download/keys{/key_id}","collaborators_url":"https://api.github.com/repos/puyvongheng/apk_youtube_download/collaborators{/collaborator}","teams_url":"https://api.github.com/repos/puyvongheng/apk_youtube_download/teams","hooks_url":"https://api.github.com/repos/puyvongheng/apk_youtube_download/hooks","issue_events_url":"https://api.github.com/repos/puyvongheng/apk_youtube_download/issues/events{/number}","events_url":"https://api.github.com/repos/puyvongheng/apk_youtube_download/events","assignees_url":"https://api.github.com/repos/puyvongheng/apk_youtube_download/assignees{/user}","branches_url":"https://api.github.com/repos/puyvongheng/apk_youtube_download/branches{/branch}","tags_url":"https://api.github.com/repos/puyvongheng/apk_youtube_download/tags","blobs_url":"https://api.github.com/repos/puyvongheng/apk_youtube_download/git/blobs{/sha}","git_tags_url":"https://api.github.com/repos/puyvongheng/apk_youtube_download/git/tags{/sha}","git_refs_url":"https://api.github.com/repos/puyvongheng/apk_youtube_download/git/refs{/sha}","trees_url":"https://api.github.com/repos/puyvongheng/apk_youtube_download/git/trees{/sha}","statuses_url":"https://api.github.com/repos/puyvongheng/apk_youtube_download/statuses/{sha}","languages_url":"https://api.github.com/repos/puyvongheng/apk_youtube_download/languages","stargazers_url":"https://api.github.com/repos/puyvongheng/apk_youtube_download/stargazers","contributors_url":"https://api.github.com/repos/puyvongheng/apk_youtube_download/contributors","subscribers_url":"https://api.github.com/repos/puyvongheng/apk_youtube_download/subscribers","subscription_url":"https://api.github.com/repos/puyvongheng/apk_youtube_download/subscription","commits_url":"https://api.github.com/repos/puyvongheng/apk_youtube_download/commits{/sha}","git_commits_url":"https://api.github.com/repos/puyvongheng/apk_youtube_download/git/commits{/sha}","comments_url":"https://api.github.com/repos/puyvongheng/apk_youtube_download/comments{/number}","issue_comment_url":"https://api.github.com/repos/puyvongheng/apk_youtube_download/issues/comments{/number}","contents_url":"https://api.github.com/repos/puyvongheng/apk_youtube_download/contents/{+path}","compare_url":"https://api.github.com/repos/puyvongheng/apk_youtube_download/compare/{base}...{head}","merges_url":"https://api.github.com/repos/puyvongheng/apk_youtube_download/merges","archive_url":"https://api.github.com/repos/puyvongheng/apk_youtube_download/{archive_format}{/ref}","downloads_url":"https://api.github.com/repos/puyvongheng/apk_youtube_download/downloads","issues_url":"https://api.github.com/repos/puyvongheng/apk_youtube_download/issues{/number}","pulls_url":"https://api.github.com/repos/puyvongheng/apk_youtube_download/pulls{/number}","milestones_url":"https://api.github.com/repos/puyvongheng/apk_youtube_download/milestones{/number}","notifications_url":"https://api.github.com/repos/puyvongheng/apk_youtube_download/notifications{?since,all,participating}","labels_url":"https://api.github.com/repos/puyvongheng/apk_youtube_download/labels{/name}","releases_url":"https://api.github.com/repos/puyvongheng/apk_youtube_download/releases{/id}","deployments_url":"https://api.github.com/repos/puyvongheng/apk_youtube_download/deployments"},"head_repository":{"id":1268852851,"node_id":"R_kgDOS6Eocw","name":"apk_youtube_download","full_name":"puyvongheng/apk_youtube_download","private":false,"owner":{"login":"puyvongheng","id":160134498,"node_id":"U_kgDOCYt1Yg","avatar_url":"https://avatars.githubusercontent.com/u/160134498?v=4","gravatar_id":"","url":"https://api.github.com/users/puyvongheng","html_url":"https://github.com/puyvongheng","followers_url":"https://api.github.com/users/puyvongheng/followers","following_url":"https://api.github.com/users/puyvongheng/following{/other_user}","gists_url":"https://api.github.com/users/puyvongheng/gists{/gist_id}","starred_url":"https://api.github.com/users/puyvongheng/starred{/owner}{/repo}","subscriptions_url":"https://api.github.com/users/puyvongheng/subscriptions","organizations_url":"https://api.github.com/users/puyvongheng/orgs","repos_url":"https://api.github.com/users/puyvongheng/repos","events_url":"https://api.github.com/users/puyvongheng/events{/privacy}","received_events_url":"https://api.github.com/users/puyvongheng/received_events","type":"User","user_view_type":"public","site_admin":false},"html_url":"https://github.com/puyvongheng/apk_youtube_download","description":null,"fork":false,"url":"https://api.github.com/repos/puyvongheng/apk_youtube_download","forks_url":"https://api.github.com/repos/puyvongheng/apk_youtube_download/forks","keys_url":"https://api.github.com/repos/puyvongheng/apk_youtube_download/keys{/key_id}","collaborators_url":"https://api.github.com/repos/puyvongheng/apk_youtube_download/collaborators{/collaborator}","teams_url":"https://api.github.com/repos/puyvongheng/apk_youtube_download/teams","hooks_url":"https://api.github.com/repos/puyvongheng/apk_youtube_download/hooks","issue_events_url":"https://api.github.com/repos/puyvongheng/apk_youtube_download/issues/events{/number}","events_url":"https://api.github.com/repos/puyvongheng/apk_youtube_download/events","assignees_url":"https://api.github.com/repos/puyvongheng/apk_youtube_download/assignees{/user}","branches_url":"https://api.github.com/repos/puyvongheng/apk_youtube_download/branches{/branch}","tags_url":"https://api.github.com/repos/puyvongheng/apk_youtube_download/tags","blobs_url":"https://api.github.com/repos/puyvongheng/apk_youtube_download/git/blobs{/sha}","git_tags_url":"https://api.github.com/repos/puyvongheng/apk_youtube_download/git/tags{/sha}","git_refs_url":"https://api.github.com/repos/puyvongheng/apk_youtube_download/git/refs{/sha}","trees_url":"https://api.github.com/repos/puyvongheng/apk_youtube_download/git/trees{/sha}","statuses_url":"https://api.github.com/repos/puyvongheng/apk_youtube_download/statuses/{sha}","languages_url":"https://api.github.com/repos/puyvongheng/apk_youtube_download/languages","stargazers_url":"https://api.github.com/repos/puyvongheng/apk_youtube_download/stargazers","contributors_url":"https://api.github.com/repos/puyvongheng/apk_youtube_download/contributors","subscribers_url":"https://api.github.com/repos/puyvongheng/apk_youtube_download/subscribers","subscription_url":"https://api.github.com/repos/puyvongheng/apk_youtube_download/subscription","commits_url":"https://api.github.com/repos/puyvongheng/apk_youtube_download/commits{/sha}","git_commits_url":"https://api.github.com/repos/puyvongheng/apk_youtube_download/git/commits{/sha}","comments_url":"https://api.github.com/repos/puyvongheng/apk_youtube_download/comments{/number}","issue_comment_url":"https://api.github.com/repos/puyvongheng/apk_youtube_download/issues/comments{/number}","contents_url":"https://api.github.com/repos/puyvongheng/apk_youtube_download/contents/{+path}","compare_url":"https://api.github.com/repos/puyvongheng/apk_youtube_download/compare/{base}...{head}","merges_url":"https://api.github.com/repos/puyvongheng/apk_youtube_download/merges","archive_url":"https://api.github.com/repos/puyvongheng/apk_youtube_download/{archive_format}{/ref}","downloads_url":"https://api.github.com/repos/puyvongheng/apk_youtube_download/downloads","issues_url":"https://api.github.com/repos/puyvongheng/apk_youtube_download/issues{/number}","pulls_url":"https://api.github.com/repos/puyvongheng/apk_youtube_download/pulls{/number}","milestones_url":"https://api.github.com/repos/puyvongheng/apk_youtube_download/milestones{/number}","notifications_url":"https://api.github.com/repos/puyvongheng/apk_youtube_download/notifications{?since,all,participating}","labels_url":"https://api.github.com/repos/puyvongheng/apk_youtube_download/labels{/name}","releases_url":"https://api.github.com/repos/puyvongheng/apk_youtube_download/releases{/id}","deployments_url":"https://api.github.com/repos/puyvongheng/apk_youtube_download/deployments"}},{"id":27486235244,"name":"Build Android APK","node_id":"WFR_kwLOS6Eoc88AAAAGZk6qbA","head_branch":"main","head_sha":"2972676981efd02419ff2625c083a12ffe82710f","path":".github/workflows/build_apk.yml","display_title":"fix: add pipefail to catch buildozer errors, always upload build log","run_number":3,"event":"push","status":"completed","conclusion":"failure","workflow_id":295580016,"check_suite_id":73957692091,"check_suite_node_id":"CS_kwDOS6Eoc88AAAARODjSuw","url":"https://api.github.com/repos/puyvongheng/apk_youtube_download/actions/runs/27486235244","html_url":"https://github.com/puyvongheng/apk_youtube_download/actions/runs/27486235244","pull_requests":[],"created_at":"2026-06-14T02:43:10Z","updated_at":"2026-06-14T02:44:23Z","actor":{"login":"puyvongheng","id":160134498,"node_id":"U_kgDOCYt1Yg","avatar_url":"https://avatars.githubusercontent.com/u/160134498?v=4","gravatar_id":"","url":"https://api.github.com/users/puyvongheng","html_url":"https://github.com/puyvongheng","followers_url":"https://api.github.com/users/puyvongheng/followers","following_url":"https://api.github.com/users/puyvongheng/following{/other_user}","gists_url":"https://api.github.com/users/puyvongheng/gists{/gist_id}","starred_url":"https://api.github.com/users/puyvongheng/starred{/owner}{/repo}","subscriptions_url":"https://api.github.com/users/puyvongheng/subscriptions","organizations_url":"https://api.github.com/users/puyvongheng/orgs","repos_url":"https://api.github.com/users/puyvongheng/repos","events_url":"https://api.github.com/users/puyvongheng/events{/privacy}","received_events_url":"https://api.github.com/users/puyvongheng/received_events","type":"User","user_view_type":"public","site_admin":false},"run_attempt":1,"referenced_workflows":[],"run_started_at":"2026-06-14T02:43:10Z","triggering_actor":{"login":"puyvongheng","id":160134498,"node_id":"U_kgDOCYt1Yg","avatar_url":"https://avatars.githubusercontent.com/u/160134498?v=4","gravatar_id":"","url":"https://api.github.com/users/puyvongheng","html_url":"https://github.com/puyvongheng","followers_url":"https://api.github.com/users/puyvongheng/followers","following_url":"https://api.github.com/users/puyvongheng/following{/other_user}","gists_url":"https://api.github.com/users/puyvongheng/gists{/gist_id}","starred_url":"https://api.github.com/users/puyvongheng/starred{/owner}{/repo}","subscriptions_url":"https://api.github.com/users/puyvongheng/subscriptions","organizations_url":"https://api.github.com/users/puyvongheng/orgs","repos_url":"https://api.github.com/users/puyvongheng/repos","events_url":"https://api.github.com/users/puyvongheng/events{/privacy}","received_events_url":"https://api.github.com/users/puyvongheng/received_events","type":"User","user_view_type":"public","site_admin":false},"jobs_url":"https://api.github.com/repos/puyvongheng/apk_youtube_download/actions/runs/27486235244/jobs","logs_url":"https://api.github.com/repos/puyvongheng/apk_youtube_download/actions/runs/27486235244/logs","check_suite_url":"https://api.github.com/repos/puyvongheng/apk_youtube_download/check-suites/73957692091","artifacts_url":"https://api.github.com/repos/puyvongheng/apk_youtube_download/actions/runs/27486235244/artifacts","cancel_url":"https://api.github.com/repos/puyvongheng/apk_youtube_download/actions/runs/27486235244/cancel","rerun_url":"https://api.github.com/repos/puyvongheng/apk_youtube_download/actions/runs/27486235244/rerun","previous_attempt_url":null,"workflow_url":"https://api.github.com/repos/puyvongheng/apk_youtube_download/actions/workflows/295580016","head_commit":{"id":"2972676981efd02419ff2625c083a12ffe82710f","tree_id":"90f697b57373e9fd5d2c600d1a11856ecd7fbc47","message":"fix: add pipefail to catch buildozer errors, always upload build log","timestamp":"2026-06-14T02:42:54Z","author":{"name":"Puyvong Heng","email":"vongheng2019@example.com"},"committer":{"name":"Puyvong Heng","email":"vongheng2019@example.com"}},"repository":{"id":1268852851,"node_id":"R_kgDOS6Eocw","name":"apk_youtube_download","full_name":"puyvongheng/apk_youtube_download","private":false,"owner":{"login":"puyvongheng","id":160134498,"node_id":"U_kgDOCYt1Yg","avatar_url":"https://avatars.githubusercontent.com/u/160134498?v=4","gravatar_id":"","url":"https://api.github.com/users/puyvongheng","html_url":"https://github.com/puyvongheng","followers_url":"https://api.github.com/users/puyvongheng/followers","following_url":"https://api.github.com/users/puyvongheng/following{/other_user}","gists_url":"https://api.github.com/users/puyvongheng/gists{/gist_id}","starred_url":"https://api.github.com/users/puyvongheng/starred{/owner}{/repo}","subscriptions_url":"https://api.github.com/users/puyvongheng/subscriptions","organizations_url":"https://api.github.com/users/puyvongheng/orgs","repos_url":"https://api.github.com/users/puyvongheng/repos","events_url":"https://api.github.com/users/puyvongheng/events{/privacy}","received_events_url":"https://api.github.com/users/puyvongheng/received_events","type":"User","user_view_type":"public","site_admin":false},"html_url":"https://github.com/puyvongheng/apk_youtube_download","description":null,"fork":false,"url":"https://api.github.com/repos/puyvongheng/apk_youtube_download","forks_url":"https://api.github.com/repos/puyvongheng/apk_youtube_download/forks","keys_url":"https://api.github.com/repos/puyvongheng/apk_youtube_download/keys{/key_id}","collaborators_url":"https://api.github.com/repos/puyvongheng/apk_youtube_download/collaborators{/collaborator}","teams_url":"https://api.github.com/repos/puyvongheng/apk_youtube_download/teams","hooks_url":"https://api.github.com/repos/puyvongheng/apk_youtube_download/hooks","issue_events_url":"https://api.github.com/repos/puyvongheng/apk_youtube_download/issues/events{/number}","events_url":"https://api.github.com/repos/puyvongheng/apk_youtube_download/events","assignees_url":"https://api.github.com/repos/puyvongheng/apk_youtube_download/assignees{/user}","branches_url":"https://api.github.com/repos/puyvongheng/apk_youtube_download/branches{/branch}","tags_url":"https://api.github.com/repos/puyvongheng/apk_youtube_download/tags","blobs_url":"https://api.github.com/repos/puyvongheng/apk_youtube_download/git/blobs{/sha}","git_tags_url":"https://api.github.com/repos/puyvongheng/apk_youtube_download/git/tags{/sha}","git_refs_url":"https://api.github.com/repos/puyvongheng/apk_youtube_download/git/refs{/sha}","trees_url":"https://api.github.com/repos/puyvongheng/apk_youtube_download/git/trees{/sha}","statuses_url":"https://api.github.com/repos/puyvongheng/apk_youtube_download/statuses/{sha}","languages_url":"https://api.github.com/repos/puyvongheng/apk_youtube_download/languages","stargazers_url":"https://api.github.com/repos/puyvongheng/apk_youtube_download/stargazers","contributors_url":"https://api.github.com/repos/puyvongheng/apk_youtube_download/contributors","subscribers_url":"https://api.github.com/repos/puyvongheng/apk_youtube_download/subscribers","subscription_url":"https://api.github.com/repos/puyvongheng/apk_youtube_download/subscription","commits_url":"https://api.github.com/repos/puyvongheng/apk_youtube_download/commits{/sha}","git_commits_url":"https://api.github.com/repos/puyvongheng/apk_youtube_download/git/commits{/sha}","comments_url":"https://api.github.com/repos/puyvongheng/apk_youtube_download/comments{/number}","issue_comment_url":"https://api.github.com/repos/puyvongheng/apk_youtube_download/issues/comments{/number}","contents_url":"https://api.github.com/repos/puyvongheng/apk_youtube_download/contents/{+path}","compare_url":"https://api.github.com/repos/puyvongheng/apk_youtube_download/compare/{base}...{head}","merges_url":"https://api.github.com/repos/puyvongheng/apk_youtube_download/merges","archive_url":"https://api.github.com/repos/puyvongheng/apk_youtube_download/{archive_format}{/ref}","downloads_url":"https://api.github.com/repos/puyvongheng/apk_youtube_download/downloads","issues_url":"https://api.github.com/repos/puyvongheng/apk_youtube_download/issues{/number}","pulls_url":"https://api.github.com/repos/puyvongheng/apk_youtube_download/pulls{/number}","milestones_url":"https://api.github.com/repos/puyvongheng/apk_youtube_download/milestones{/number}","notifications_url":"https://api.github.com/repos/puyvongheng/apk_youtube_download/notifications{?since,all,participating}","labels_url":"https://api.github.com/repos/puyvongheng/apk_youtube_download/labels{/name}","releases_url":"https://api.github.com/repos/puyvongheng/apk_youtube_download/releases{/id}","deployments_url":"https://api.github.com/repos/puyvongheng/apk_youtube_download/deployments"},"head_repository":{"id":1268852851,"node_id":"R_kgDOS6Eocw","name":"apk_youtube_download","full_name":"puyvongheng/apk_youtube_download","private":false,"owner":{"login":"puyvongheng","id":160134498,"node_id":"U_kgDOCYt1Yg","avatar_url":"https://avatars.githubusercontent.com/u/160134498?v=4","gravatar_id":"","url":"https://api.github.com/users/puyvongheng","html_url":"https://github.com/puyvongheng","followers_url":"https://api.github.com/users/puyvongheng/followers","following_url":"https://api.github.com/users/puyvongheng/following{/other_user}","gists_url":"https://api.github.com/users/puyvongheng/gists{/gist_id}","starred_url":"https://api.github.com/users/puyvongheng/starred{/owner}{/repo}","subscriptions_url":"https://api.github.com/users/puyvongheng/subscriptions","organizations_url":"https://api.github.com/users/puyvongheng/orgs","repos_url":"https://api.github.com/users/puyvongheng/repos","events_url":"https://api.github.com/users/puyvongheng/events{/privacy}","received_events_url":"https://api.github.com/users/puyvongheng/received_events","type":"User","user_view_type":"public","site_admin":false},"html_url":"https://github.com/puyvongheng/apk_youtube_download","description":null,"fork":false,"url":"https://api.github.com/repos/puyvongheng/apk_youtube_download","forks_url":"https://api.github.com/repos/puyvongheng/apk_youtube_download/forks","keys_url":"https://api.github.com/repos/puyvongheng/apk_youtube_download/keys{/key_id}","collaborators_url":"https://api.github.com/repos/puyvongheng/apk_youtube_download/collaborators{/collaborator}","teams_url":"https://api.github.com/repos/puyvongheng/apk_youtube_download/teams","hooks_url":"https://api.github.com/repos/puyvongheng/apk_youtube_download/hooks","issue_events_url":"https://api.github.com/repos/puyvongheng/apk_youtube_download/issues/events{/number}","events_url":"https://api.github.com/repos/puyvongheng/apk_youtube_download/events","assignees_url":"https://api.github.com/repos/puyvongheng/apk_youtube_download/assignees{/user}","branches_url":"https://api.github.com/repos/puyvongheng/apk_youtube_download/branches{/branch}","tags_url":"https://api.github.com/repos/puyvongheng/apk_youtube_download/tags","blobs_url":"https://api.github.com/repos/puyvongheng/apk_youtube_download/git/blobs{/sha}","git_tags_url":"https://api.github.com/repos/puyvongheng/apk_youtube_download/git/tags{/sha}","git_refs_url":"https://api.github.com/repos/puyvongheng/apk_youtube_download/git/refs{/sha}","trees_url":"https://api.github.com/repos/puyvongheng/apk_youtube_download/git/trees{/sha}","statuses_url":"https://api.github.com/repos/puyvongheng/apk_youtube_download/statuses/{sha}","languages_url":"https://api.github.com/repos/puyvongheng/apk_youtube_download/languages","stargazers_url":"https://api.github.com/repos/puyvongheng/apk_youtube_download/stargazers","contributors_url":"https://api.github.com/repos/puyvongheng/apk_youtube_download/contributors","subscribers_url":"https://api.github.com/repos/puyvongheng/apk_youtube_download/subscribers","subscription_url":"https://api.github.com/repos/puyvongheng/apk_youtube_download/subscription","commits_url":"https://api.github.com/repos/puyvongheng/apk_youtube_download/commits{/sha}","git_commits_url":"https://api.github.com/repos/puyvongheng/apk_youtube_download/git/commits{/sha}","comments_url":"https://api.github.com/repos/puyvongheng/apk_youtube_download/comments{/number}","issue_comment_url":"https://api.github.com/repos/puyvongheng/apk_youtube_download/issues/comments{/number}","contents_url":"https://api.github.com/repos/puyvongheng/apk_youtube_download/contents/{+path}","compare_url":"https://api.github.com/repos/puyvongheng/apk_youtube_download/compare/{base}...{head}","merges_url":"https://api.github.com/repos/puyvongheng/apk_youtube_download/merges","archive_url":"https://api.github.com/repos/puyvongheng/apk_youtube_download/{archive_format}{/ref}","downloads_url":"https://api.github.com/repos/puyvongheng/apk_youtube_download/downloads","issues_url":"https://api.github.com/repos/puyvongheng/apk_youtube_download/issues{/number}","pulls_url":"https://api.github.com/repos/puyvongheng/apk_youtube_download/pulls{/number}","milestones_url":"https://api.github.com/repos/puyvongheng/apk_youtube_download/milestones{/number}","notifications_url":"https://api.github.com/repos/puyvongheng/apk_youtube_download/notifications{?since,all,participating}","labels_url":"https://api.github.com/repos/puyvongheng/apk_youtube_download/labels{/name}","releases_url":"https://api.github.com/repos/puyvongheng/apk_youtube_download/releases{/id}","deployments_url":"https://api.github.com/repos/puyvongheng/apk_youtube_download/deployments"}},{"id":27486178625,"name":"Build Android APK","node_id":"WFR_kwLOS6Eoc88AAAAGZk3NQQ","head_branch":"main","head_sha":"463806f119c4c89ef50b1fb0ebb2919525606de8","path":".github/workflows/build_apk.yml","display_title":"fix: remove libtinfo5 (not on Ubuntu 22.04), fix workflow dependencies","run_number":2,"event":"push","status":"completed","conclusion":"failure","workflow_id":295580016,"check_suite_id":73957541411,"check_suite_node_id":"CS_kwDOS6Eoc88AAAARODaGIw","url":"https://api.github.com/repos/puyvongheng/apk_youtube_download/actions/runs/27486178625","html_url":"https://github.com/puyvongheng/apk_youtube_download/actions/runs/27486178625","pull_requests":[],"created_at":"2026-06-14T02:40:11Z","updated_at":"2026-06-14T02:41:33Z","actor":{"login":"puyvongheng","id":160134498,"node_id":"U_kgDOCYt1Yg","avatar_url":"https://avatars.githubusercontent.com/u/160134498?v=4","gravatar_id":"","url":"https://api.github.com/users/puyvongheng","html_url":"https://github.com/puyvongheng","followers_url":"https://api.github.com/users/puyvongheng/followers","following_url":"https://api.github.com/users/puyvongheng/following{/other_user}","gists_url":"https://api.github.com/users/puyvongheng/gists{/gist_id}","starred_url":"https://api.github.com/users/puyvongheng/starred{/owner}{/repo}","subscriptions_url":"https://api.github.com/users/puyvongheng/subscriptions","organizations_url":"https://api.github.com/users/puyvongheng/orgs","repos_url":"https://api.github.com/users/puyvongheng/repos","events_url":"https://api.github.com/users/puyvongheng/events{/privacy}","received_events_url":"https://api.github.com/users/puyvongheng/received_events","type":"User","user_view_type":"public","site_admin":false},"run_attempt":1,"referenced_workflows":[],"run_started_at":"2026-06-14T02:40:11Z","triggering_actor":{"login":"puyvongheng","id":160134498,"node_id":"U_kgDOCYt1Yg","avatar_url":"https://avatars.githubusercontent.com/u/160134498?v=4","gravatar_id":"","url":"https://api.github.com/users/puyvongheng","html_url":"https://github.com/puyvongheng","followers_url":"https://api.github.com/users/puyvongheng/followers","following_url":"https://api.github.com/users/puyvongheng/following{/other_user}","gists_url":"https://api.github.com/users/puyvongheng/gists{/gist_id}","starred_url":"https://api.github.com/users/puyvongheng/starred{/owner}{/repo}","subscriptions_url":"https://api.github.com/users/puyvongheng/subscriptions","organizations_url":"https://api.github.com/users/puyvongheng/orgs","repos_url":"https://api.github.com/users/puyvongheng/repos","events_url":"https://api.github.com/users/puyvongheng/events{/privacy}","received_events_url":"https://api.github.com/users/puyvongheng/received_events","type":"User","user_view_type":"public","site_admin":false},"jobs_url":"https://api.github.com/repos/puyvongheng/apk_youtube_download/actions/runs/27486178625/jobs","logs_url":"https://api.github.com/repos/puyvongheng/apk_youtube_download/actions/runs/27486178625/logs","check_suite_url":"https://api.github.com/repos/puyvongheng/apk_youtube_download/check-suites/73957541411","artifacts_url":"https://api.github.com/repos/puyvongheng/apk_youtube_download/actions/runs/27486178625/artifacts","cancel_url":"https://api.github.com/repos/puyvongheng/apk_youtube_download/actions/runs/27486178625/cancel","rerun_url":"https://api.github.com/repos/puyvongheng/apk_youtube_download/actions/runs/27486178625/rerun","previous_attempt_url":null,"workflow_url":"https://api.github.com/repos/puyvongheng/apk_youtube_download/actions/workflows/295580016","head_commit":{"id":"463806f119c4c89ef50b1fb0ebb2919525606de8","tree_id":"391f49da498b6a18761a47515fcdfb842b687195","message":"fix: remove libtinfo5 (not on Ubuntu 22.04), fix workflow dependencies","timestamp":"2026-06-14T02:39:55Z","author":{"name":"Puyvong Heng","email":"vongheng2019@example.com"},"committer":{"name":"Puyvong Heng","email":"vongheng2019@example.com"}},"repository":{"id":1268852851,"node_id":"R_kgDOS6Eocw","name":"apk_youtube_download","full_name":"puyvongheng/apk_youtube_download","private":false,"owner":{"login":"puyvongheng","id":160134498,"node_id":"U_kgDOCYt1Yg","avatar_url":"https://avatars.githubusercontent.com/u/160134498?v=4","gravatar_id":"","url":"https://api.github.com/users/puyvongheng","html_url":"https://github.com/puyvongheng","followers_url":"https://api.github.com/users/puyvongheng/followers","following_url":"https://api.github.com/users/puyvongheng/following{/other_user}","gists_url":"https://api.github.com/users/puyvongheng/gists{/gist_id}","starred_url":"https://api.github.com/users/puyvongheng/starred{/owner}{/repo}","subscriptions_url":"https://api.github.com/users/puyvongheng/subscriptions","organizations_url":"https://api.github.com/users/puyvongheng/orgs","repos_url":"https://api.github.com/users/puyvongheng/repos","events_url":"https://api.github.com/users/puyvongheng/events{/privacy}","received_events_url":"https://api.github.com/users/puyvongheng/received_events","type":"User","user_view_type":"public","site_admin":false},"html_url":"https://github.com/puyvongheng/apk_youtube_download","description":null,"fork":false,"url":"https://api.github.com/repos/puyvongheng/apk_youtube_download","forks_url":"https://api.github.com/repos/puyvongheng/apk_youtube_download/forks","keys_url":"https://api.github.com/repos/puyvongheng/apk_youtube_download/keys{/key_id}","collaborators_url":"https://api.github.com/repos/puyvongheng/apk_youtube_download/collaborators{/collaborator}","teams_url":"https://api.github.com/repos/puyvongheng/apk_youtube_download/teams","hooks_url":"https://api.github.com/repos/puyvongheng/apk_youtube_download/hooks","issue_events_url":"https://api.github.com/repos/puyvongheng/apk_youtube_download/issues/events{/number}","events_url":"https://api.github.com/repos/puyvongheng/apk_youtube_download/events","assignees_url":"https://api.github.com/repos/puyvongheng/apk_youtube_download/assignees{/user}","branches_url":"https://api.github.com/repos/puyvongheng/apk_youtube_download/branches{/branch}","tags_url":"https://api.github.com/repos/puyvongheng/apk_youtube_download/tags","blobs_url":"https://api.github.com/repos/puyvongheng/apk_youtube_download/git/blobs{/sha}","git_tags_url":"https://api.github.com/repos/puyvongheng/apk_youtube_download/git/tags{/sha}","git_refs_url":"https://api.github.com/repos/puyvongheng/apk_youtube_download/git/refs{/sha}","trees_url":"https://api.github.com/repos/puyvongheng/apk_youtube_download/git/trees{/sha}","statuses_url":"https://api.github.com/repos/puyvongheng/apk_youtube_download/statuses/{sha}","languages_url":"https://api.github.com/repos/puyvongheng/apk_youtube_download/languages","stargazers_url":"https://api.github.com/repos/puyvongheng/apk_youtube_download/stargazers","contributors_url":"https://api.github.com/repos/puyvongheng/apk_youtube_download/contributors","subscribers_url":"https://api.github.com/repos/puyvongheng/apk_youtube_download/subscribers","subscription_url":"https://api.github.com/repos/puyvongheng/apk_youtube_download/subscription","commits_url":"https://api.github.com/repos/puyvongheng/apk_youtube_download/commits{/sha}","git_commits_url":"https://api.github.com/repos/puyvongheng/apk_youtube_download/git/commits{/sha}","comments_url":"https://api.github.com/repos/puyvongheng/apk_youtube_download/comments{/number}","issue_comment_url":"https://api.github.com/repos/puyvongheng/apk_youtube_download/issues/comments{/number}","contents_url":"https://api.github.com/repos/puyvongheng/apk_youtube_download/contents/{+path}","compare_url":"https://api.github.com/repos/puyvongheng/apk_youtube_download/compare/{base}...{head}","merges_url":"https://api.github.com/repos/puyvongheng/apk_youtube_download/merges","archive_url":"https://api.github.com/repos/puyvongheng/apk_youtube_download/{archive_format}{/ref}","downloads_url":"https://api.github.com/repos/puyvongheng/apk_youtube_download/downloads","issues_url":"https://api.github.com/repos/puyvongheng/apk_youtube_download/issues{/number}","pulls_url":"https://api.github.com/repos/puyvongheng/apk_youtube_download/pulls{/number}","milestones_url":"https://api.github.com/repos/puyvongheng/apk_youtube_download/milestones{/number}","notifications_url":"https://api.github.com/repos/puyvongheng/apk_youtube_download/notifications{?since,all,participating}","labels_url":"https://api.github.com/repos/puyvongheng/apk_youtube_download/labels{/name}","releases_url":"https://api.github.com/repos/puyvongheng/apk_youtube_download/releases{/id}","deployments_url":"https://api.github.com/repos/puyvongheng/apk_youtube_download/deployments"},"head_repository":{"id":1268852851,"node_id":"R_kgDOS6Eocw","name":"apk_youtube_download","full_name":"puyvongheng/apk_youtube_download","private":false,"owner":{"login":"puyvongheng","id":160134498,"node_id":"U_kgDOCYt1Yg","avatar_url":"https://avatars.githubusercontent.com/u/160134498?v=4","gravatar_id":"","url":"https://api.github.com/users/puyvongheng","html_url":"https://github.com/puyvongheng","followers_url":"https://api.github.com/users/puyvongheng/followers","following_url":"https://api.github.com/users/puyvongheng/following{/other_user}","gists_url":"https://api.github.com/users/puyvongheng/gists{/gist_id}","starred_url":"https://api.github.com/users/puyvongheng/starred{/owner}{/repo}","subscriptions_url":"https://api.github.com/users/puyvongheng/subscriptions","organizations_url":"https://api.github.com/users/puyvongheng/orgs","repos_url":"https://api.github.com/users/puyvongheng/repos","events_url":"https://api.github.com/users/puyvongheng/events{/privacy}","received_events_url":"https://api.github.com/users/puyvongheng/received_events","type":"User","user_view_type":"public","site_admin":false},"html_url":"https://github.com/puyvongheng/apk_youtube_download","description":null,"fork":false,"url":"https://api.github.com/repos/puyvongheng/apk_youtube_download","forks_url":"https://api.github.com/repos/puyvongheng/apk_youtube_download/forks","keys_url":"https://api.github.com/repos/puyvongheng/apk_youtube_download/keys{/key_id}","collaborators_url":"https://api.github.com/repos/puyvongheng/apk_youtube_download/collaborators{/collaborator}","teams_url":"https://api.github.com/repos/puyvongheng/apk_youtube_download/teams","hooks_url":"https://api.github.com/repos/puyvongheng/apk_youtube_download/hooks","issue_events_url":"https://api.github.com/repos/puyvongheng/apk_youtube_download/issues/events{/number}","events_url":"https://api.github.com/repos/puyvongheng/apk_youtube_download/events","assignees_url":"https://api.github.com/repos/puyvongheng/apk_youtube_download/assignees{/user}","branches_url":"https://api.github.com/repos/puyvongheng/apk_youtube_download/branches{/branch}","tags_url":"https://api.github.com/repos/puyvongheng/apk_youtube_download/tags","blobs_url":"https://api.github.com/repos/puyvongheng/apk_youtube_download/git/blobs{/sha}","git_tags_url":"https://api.github.com/repos/puyvongheng/apk_youtube_download/git/tags{/sha}","git_refs_url":"https://api.github.com/repos/puyvongheng/apk_youtube_download/git/refs{/sha}","trees_url":"https://api.github.com/repos/puyvongheng/apk_youtube_download/git/trees{/sha}","statuses_url":"https://api.github.com/repos/puyvongheng/apk_youtube_download/statuses/{sha}","languages_url":"https://api.github.com/repos/puyvongheng/apk_youtube_download/languages","stargazers_url":"https://api.github.com/repos/puyvongheng/apk_youtube_download/stargazers","contributors_url":"https://api.github.com/repos/puyvongheng/apk_youtube_download/contributors","subscribers_url":"https://api.github.com/repos/puyvongheng/apk_youtube_download/subscribers","subscription_url":"https://api.github.com/repos/puyvongheng/apk_youtube_download/subscription","commits_url":"https://api.github.com/repos/puyvongheng/apk_youtube_download/commits{/sha}","git_commits_url":"https://api.github.com/repos/puyvongheng/apk_youtube_download/git/commits{/sha}","comments_url":"https://api.github.com/repos/puyvongheng/apk_youtube_download/comments{/number}","issue_comment_url":"https://api.github.com/repos/puyvongheng/apk_youtube_download/issues/comments{/number}","contents_url":"https://api.github.com/repos/puyvongheng/apk_youtube_download/contents/{+path}","compare_url":"https://api.github.com/repos/puyvongheng/apk_youtube_download/compare/{base}...{head}","merges_url":"https://api.github.com/repos/puyvongheng/apk_youtube_download/merges","archive_url":"https://api.github.com/repos/puyvongheng/apk_youtube_download/{archive_format}{/ref}","downloads_url":"https://api.github.com/repos/puyvongheng/apk_youtube_download/downloads","issues_url":"https://api.github.com/repos/puyvongheng/apk_youtube_download/issues{/number}","pulls_url":"https://api.github.com/repos/puyvongheng/apk_youtube_download/pulls{/number}","milestones_url":"https://api.github.com/repos/puyvongheng/apk_youtube_download/milestones{/number}","notifications_url":"https://api.github.com/repos/puyvongheng/apk_youtube_download/notifications{?since,all,participating}","labels_url":"https://api.github.com/repos/puyvongheng/apk_youtube_download/labels{/name}","releases_url":"https://api.github.com/repos/puyvongheng/apk_youtube_download/releases{/id}","deployments_url":"https://api.github.com/repos/puyvongheng/apk_youtube_download/deployments"}},{"id":27486099205,"name":"Build Android APK","node_id":"WFR_kwLOS6Eoc88AAAAGZkyXBQ","head_branch":"main","head_sha":"99cea5357403d74c9e5d963d6f142fd0d4a79027","path":".github/workflows/build_apk.yml","display_title":"Initial commit: YouTube Downloader Kivy app with GitHub Actions APK b…","run_number":1,"event":"push","status":"completed","conclusion":"failure","workflow_id":295580016,"check_suite_id":73957325452,"check_suite_node_id":"CS_kwDOS6Eoc88AAAARODM6jA","url":"https://api.github.com/repos/puyvongheng/apk_youtube_download/actions/runs/27486099205","html_url":"https://github.com/puyvongheng/apk_youtube_download/actions/runs/27486099205","pull_requests":[],"created_at":"2026-06-14T02:36:03Z","updated_at":"2026-06-14T02:37:22Z","actor":{"login":"puyvongheng","id":160134498,"node_id":"U_kgDOCYt1Yg","avatar_url":"https://avatars.githubusercontent.com/u/160134498?v=4","gravatar_id":"","url":"https://api.github.com/users/puyvongheng","html_url":"https://github.com/puyvongheng","followers_url":"https://api.github.com/users/puyvongheng/followers","following_url":"https://api.github.com/users/puyvongheng/following{/other_user}","gists_url":"https://api.github.com/users/puyvongheng/gists{/gist_id}","starred_url":"https://api.github.com/users/puyvongheng/starred{/owner}{/repo}","subscriptions_url":"https://api.github.com/users/puyvongheng/subscriptions","organizations_url":"https://api.github.com/users/puyvongheng/orgs","repos_url":"https://api.github.com/users/puyvongheng/repos","events_url":"https://api.github.com/users/puyvongheng/events{/privacy}","received_events_url":"https://api.github.com/users/puyvongheng/received_events","type":"User","user_view_type":"public","site_admin":false},"run_attempt":1,"referenced_workflows":[],"run_started_at":"2026-06-14T02:36:03Z","triggering_actor":{"login":"puyvongheng","id":160134498,"node_id":"U_kgDOCYt1Yg","avatar_url":"https://avatars.githubusercontent.com/u/160134498?v=4","gravatar_id":"","url":"https://api.github.com/users/puyvongheng","html_url":"https://github.com/puyvongheng","followers_url":"https://api.github.com/users/puyvongheng/followers","following_url":"https://api.github.com/users/puyvongheng/following{/other_user}","gists_url":"https://api.github.com/users/puyvongheng/gists{/gist_id}","starred_url":"https://api.github.com/users/puyvongheng/starred{/owner}{/repo}","subscriptions_url":"https://api.github.com/users/puyvongheng/subscriptions","organizations_url":"https://api.github.com/users/puyvongheng/orgs","repos_url":"https://api.github.com/users/puyvongheng/repos","events_url":"https://api.github.com/users/puyvongheng/events{/privacy}","received_events_url":"https://api.github.com/users/puyvongheng/received_events","type":"User","user_view_type":"public","site_admin":false},"jobs_url":"https://api.github.com/repos/puyvongheng/apk_youtube_download/actions/runs/27486099205/jobs","logs_url":"https://api.github.com/repos/puyvongheng/apk_youtube_download/actions/runs/27486099205/logs","check_suite_url":"https://api.github.com/repos/puyvongheng/apk_youtube_download/check-suites/73957325452","artifacts_url":"https://api.github.com/repos/puyvongheng/apk_youtube_download/actions/runs/27486099205/artifacts","cancel_url":"https://api.github.com/repos/puyvongheng/apk_youtube_download/actions/runs/27486099205/cancel","rerun_url":"https://api.github.com/repos/puyvongheng/apk_youtube_download/actions/runs/27486099205/rerun","previous_attempt_url":null,"workflow_url":"https://api.github.com/repos/puyvongheng/apk_youtube_download/actions/workflows/295580016","head_commit":{"id":"99cea5357403d74c9e5d963d6f142fd0d4a79027","tree_id":"60a1658b5a7dadf708ebf7b4727a3ebf32359607","message":"Initial commit: YouTube Downloader Kivy app with GitHub Actions APK build","timestamp":"2026-06-14T02:34:55Z","author":{"name":"Puyvong Heng","email":"vongheng2019@example.com"},"committer":{"name":"Puyvong Heng","email":"vongheng2019@example.com"}},"repository":{"id":1268852851,"node_id":"R_kgDOS6Eocw","name":"apk_youtube_download","full_name":"puyvongheng/apk_youtube_download","private":false,"owner":{"login":"puyvongheng","id":160134498,"node_id":"U_kgDOCYt1Yg","avatar_url":"https://avatars.githubusercontent.com/u/160134498?v=4","gravatar_id":"","url":"https://api.github.com/users/puyvongheng","html_url":"https://github.com/puyvongheng","followers_url":"https://api.github.com/users/puyvongheng/followers","following_url":"https://api.github.com/users/puyvongheng/following{/other_user}","gists_url":"https://api.github.com/users/puyvongheng/gists{/gist_id}","starred_url":"https://api.github.com/users/puyvongheng/starred{/owner}{/repo}","subscriptions_url":"https://api.github.com/users/puyvongheng/subscriptions","organizations_url":"https://api.github.com/users/puyvongheng/orgs","repos_url":"https://api.github.com/users/puyvongheng/repos","events_url":"https://api.github.com/users/puyvongheng/events{/privacy}","received_events_url":"https://api.github.com/users/puyvongheng/received_events","type":"User","user_view_type":"public","site_admin":false},"html_url":"https://github.com/puyvongheng/apk_youtube_download","description":null,"fork":false,"url":"https://api.github.com/repos/puyvongheng/apk_youtube_download","forks_url":"https://api.github.com/repos/puyvongheng/apk_youtube_download/forks","keys_url":"https://api.github.com/repos/puyvongheng/apk_youtube_download/keys{/key_id}","collaborators_url":"https://api.github.com/repos/puyvongheng/apk_youtube_download/collaborators{/collaborator}","teams_url":"https://api.github.com/repos/puyvongheng/apk_youtube_download/teams","hooks_url":"https://api.github.com/repos/puyvongheng/apk_youtube_download/hooks","issue_events_url":"https://api.github.com/repos/puyvongheng/apk_youtube_download/issues/events{/number}","events_url":"https://api.github.com/repos/puyvongheng/apk_youtube_download/events","assignees_url":"https://api.github.com/repos/puyvongheng/apk_youtube_download/assignees{/user}","branches_url":"https://api.github.com/repos/puyvongheng/apk_youtube_download/branches{/branch}","tags_url":"https://api.github.com/repos/puyvongheng/apk_youtube_download/tags","blobs_url":"https://api.github.com/repos/puyvongheng/apk_youtube_download/git/blobs{/sha}","git_tags_url":"https://api.github.com/repos/puyvongheng/apk_youtube_download/git/tags{/sha}","git_refs_url":"https://api.github.com/repos/puyvongheng/apk_youtube_download/git/refs{/sha}","trees_url":"https://api.github.com/repos/puyvongheng/apk_youtube_download/git/trees{/sha}","statuses_url":"https://api.github.com/repos/puyvongheng/apk_youtube_download/statuses/{sha}","languages_url":"https://api.github.com/repos/puyvongheng/apk_youtube_download/languages","stargazers_url":"https://api.github.com/repos/puyvongheng/apk_youtube_download/stargazers","contributors_url":"https://api.github.com/repos/puyvongheng/apk_youtube_download/contributors","subscribers_url":"https://api.github.com/repos/puyvongheng/apk_youtube_download/subscribers","subscription_url":"https://api.github.com/repos/puyvongheng/apk_youtube_download/subscription","commits_url":"https://api.github.com/repos/puyvongheng/apk_youtube_download/commits{/sha}","git_commits_url":"https://api.github.com/repos/puyvongheng/apk_youtube_download/git/commits{/sha}","comments_url":"https://api.github.com/repos/puyvongheng/apk_youtube_download/comments{/number}","issue_comment_url":"https://api.github.com/repos/puyvongheng/apk_youtube_download/issues/comments{/number}","contents_url":"https://api.github.com/repos/puyvongheng/apk_youtube_download/contents/{+path}","compare_url":"https://api.github.com/repos/puyvongheng/apk_youtube_download/compare/{base}...{head}","merges_url":"https://api.github.com/repos/puyvongheng/apk_youtube_download/merges","archive_url":"https://api.github.com/repos/puyvongheng/apk_youtube_download/{archive_format}{/ref}","downloads_url":"https://api.github.com/repos/puyvongheng/apk_youtube_download/downloads","issues_url":"https://api.github.com/repos/puyvongheng/apk_youtube_download/issues{/number}","pulls_url":"https://api.github.com/repos/puyvongheng/apk_youtube_download/pulls{/number}","milestones_url":"https://api.github.com/repos/puyvongheng/apk_youtube_download/milestones{/number}","notifications_url":"https://api.github.com/repos/puyvongheng/apk_youtube_download/notifications{?since,all,participating}","labels_url":"https://api.github.com/repos/puyvongheng/apk_youtube_download/labels{/name}","releases_url":"https://api.github.com/repos/puyvongheng/apk_youtube_download/releases{/id}","deployments_url":"https://api.github.com/repos/puyvongheng/apk_youtube_download/deployments"},"head_repository":{"id":1268852851,"node_id":"R_kgDOS6Eocw","name":"apk_youtube_download","full_name":"puyvongheng/apk_youtube_download","private":false,"owner":{"login":"puyvongheng","id":160134498,"node_id":"U_kgDOCYt1Yg","avatar_url":"https://avatars.githubusercontent.com/u/160134498?v=4","gravatar_id":"","url":"https://api.github.com/users/puyvongheng","html_url":"https://github.com/puyvongheng","followers_url":"https://api.github.com/users/puyvongheng/followers","following_url":"https://api.github.com/users/puyvongheng/following{/other_user}","gists_url":"https://api.github.com/users/puyvongheng/gists{/gist_id}","starred_url":"https://api.github.com/users/puyvongheng/starred{/owner}{/repo}","subscriptions_url":"https://api.github.com/users/puyvongheng/subscriptions","organizations_url":"https://api.github.com/users/puyvongheng/orgs","repos_url":"https://api.github.com/users/puyvongheng/repos","events_url":"https://api.github.com/users/puyvongheng/events{/privacy}","received_events_url":"https://api.github.com/users/puyvongheng/received_events","type":"User","user_view_type":"public","site_admin":false},"html_url":"https://github.com/puyvongheng/apk_youtube_download","description":null,"fork":false,"url":"https://api.github.com/repos/puyvongheng/apk_youtube_download","forks_url":"https://api.github.com/repos/puyvongheng/apk_youtube_download/forks","keys_url":"https://api.github.com/repos/puyvongheng/apk_youtube_download/keys{/key_id}","collaborators_url":"https://api.github.com/repos/puyvongheng/apk_youtube_download/collaborators{/collaborator}","teams_url":"https://api.github.com/repos/puyvongheng/apk_youtube_download/teams","hooks_url":"https://api.github.com/repos/puyvongheng/apk_youtube_download/hooks","issue_events_url":"https://api.github.com/repos/puyvongheng/apk_youtube_download/issues/events{/number}","events_url":"https://api.github.com/repos/puyvongheng/apk_youtube_download/events","assignees_url":"https://api.github.com/repos/puyvongheng/apk_youtube_download/assignees{/user}","branches_url":"https://api.github.com/repos/puyvongheng/apk_youtube_download/branches{/branch}","tags_url":"https://api.github.com/repos/puyvongheng/apk_youtube_download/tags","blobs_url":"https://api.github.com/repos/puyvongheng/apk_youtube_download/git/blobs{/sha}","git_tags_url":"https://api.github.com/repos/puyvongheng/apk_youtube_download/git/tags{/sha}","git_refs_url":"https://api.github.com/repos/puyvongheng/apk_youtube_download/git/refs{/sha}","trees_url":"https://api.github.com/repos/puyvongheng/apk_youtube_download/git/trees{/sha}","statuses_url":"https://api.github.com/repos/puyvongheng/apk_youtube_download/statuses/{sha}","languages_url":"https://api.github.com/repos/puyvongheng/apk_youtube_download/languages","stargazers_url":"https://api.github.com/repos/puyvongheng/apk_youtube_download/stargazers","contributors_url":"https://api.github.com/repos/puyvongheng/apk_youtube_download/contributors","subscribers_url":"https://api.github.com/repos/puyvongheng/apk_youtube_download/subscribers","subscription_url":"https://api.github.com/repos/puyvongheng/apk_youtube_download/subscription","commits_url":"https://api.github.com/repos/puyvongheng/apk_youtube_download/commits{/sha}","git_commits_url":"https://api.github.com/repos/puyvongheng/apk_youtube_download/git/commits{/sha}","comments_url":"https://api.github.com/repos/puyvongheng/apk_youtube_download/comments{/number}","issue_comment_url":"https://api.github.com/repos/puyvongheng/apk_youtube_download/issues/comments{/number}","contents_url":"https://api.github.com/repos/puyvongheng/apk_youtube_download/contents/{+path}","compare_url":"https://api.github.com/repos/puyvongheng/apk_youtube_download/compare/{base}...{head}","merges_url":"https://api.github.com/repos/puyvongheng/apk_youtube_download/merges","archive_url":"https://api.github.com/repos/puyvongheng/apk_youtube_download/{archive_format}{/ref}","downloads_url":"https://api.github.com/repos/puyvongheng/apk_youtube_download/downloads","issues_url":"https://api.github.com/repos/puyvongheng/apk_youtube_download/issues{/number}","pulls_url":"https://api.github.com/repos/puyvongheng/apk_youtube_download/pulls{/number}","milestones_url":"https://api.github.com/repos/puyvongheng/apk_youtube_download/milestones{/number}","notifications_url":"https://api.github.com/repos/puyvongheng/apk_youtube_download/notifications{?since,all,participating}","labels_url":"https://api.github.com/repos/puyvongheng/apk_youtube_download/labels{/name}","releases_url":"https://api.github.com/repos/puyvongheng/apk_youtube_download/releases{/id}","deployments_url":"https://api.github.com/repos/puyvongheng/apk_youtube_download/deployments"}}]}